osbornehoffman/__init__.py
osbornehoffman/account.py
osbornehoffman/server.py
osbornehoffman/tables.py
osbornehoffman-1.0.3.dist-info/LICENSE
osbornehoffman-1.0.3.dist-info/METADATA
osbornehoffman-1.0.3.dist-info/WHEEL
osbornehoffman-1.0.3.dist-info/top_level.txt
osbornehoffman-1.0.3.dist-info/RECORD
