Metadata-Version: 2.1
Name: osbornehoffman
Version: 1.0.3
Summary: Python 3 package to interface with Osborne Hoffman panels.
Home-page: https://github.com/wichers/python-osbornehoffman
Author: wichers
Author-email: wichers@users.noreply.github.com
License: MIT
Classifier: Programming Language :: Python :: 3
Classifier: License :: OSI Approved :: MIT License
Classifier: Operating System :: OS Independent
Requires-Python: >=3.8
License-File: LICENSE
Requires-Dist: pycryptodome >=3.14.0
Requires-Dist: crc >=6.1.1
